ndx_ophys_devices/spec/ndx-ophys-devices.extensions.yaml
ndx_ophys_devices/spec/ndx-ophys-devices.namespace.yaml
ndx_ophys_devices/__init__.py
ndx_ophys_devices/testing/__init__.py
ndx_ophys_devices/testing/_mock.py
ndx_ophys_devices/widgets/README.md
ndx_ophys_devices/widgets/__init__.py
ndx_ophys_devices/widgets/tetrode_series_widget.py
ndx_ophys_devices-0.3.1.dist-info/METADATA
ndx_ophys_devices-0.3.1.dist-info/WHEEL
ndx_ophys_devices-0.3.1.dist-info/licenses/LICENSE.txt
ndx_ophys_devices-0.3.1.dist-info/RECORD
