Metadata-Version: 2.4
Name: ndx-ophys-devices
Version: 0.3.1
Summary: This is an NWB extension for storing metadata of devices used in optical experimental setup (microscopy, fiber photometry, optogenetic stimulation etc.)
Project-URL: Homepage, https://github.com/catalystneuro/ndx-ophys-devices
Project-URL: Documentation, https://ndx-ophys-devices.readthedocs.io/
Project-URL: Bug Tracker, https://github.com/catalystneuro/ndx-ophys-devices/issues
Project-URL: Discussions, https://github.com/catalystneuro/ndx-ophys-devices/discussions
Project-URL: Changelog, https://github.com/catalystneuro/ndx-ophys-devices/blob/main/CHANGELOG.md
Author-email: Alessandra Trapani <alessandra.trapani@catalystneuro.com>, Paul Adkisson-Floro <paul.adkisson@catalystneuro.com>
License: BSD-3
License-File: LICENSE.txt
Keywords: NWB,NeurodataWithoutBorders,ndx-extension,nwb-extension
Classifier: Intended Audience :: Developers
Classifier: Intended Audience :: Science/Research
Classifier: License :: OSI Approved :: BSD License
Classifier: Programming Language :: Python :: 3.10
Requires-Dist: hdmf>=3.13.0
Requires-Dist: pynwb>=3.1.0
